examples/__init__.py
examples/demo.py
examples/simple_demo.py
examples/simple_demo_v3.py
unittestcases/__init__.py
unittestcases/path_util.py
unittestcases/xinge3_unittest.py
unittestcases/xinge_unittest.py
xinge_push/__init__.py
xinge_push/constant.py
xinge_push/message.py
xinge_push/schedule.py
xinge_push/style.py
xinge_push/xinge.py
xinge_push/xinge3.py
xinge-2.0.4.dist-info/METADATA
xinge-2.0.4.dist-info/WHEEL
xinge-2.0.4.dist-info/top_level.txt
xinge-2.0.4.dist-info/zip-safe
xinge-2.0.4.dist-info/RECORD
