Metadata-Version: 2.1
Name: xinge
Version: 2.0.4
Summary: xinge Push API for Python(http://xg.qq.com).
Home-page: https://github.com/jie17/xinge-api-python
Author: observer
Author-email: 764664@gmail.com
License: MIT
Keywords: xinge,Android Push,iOS Push,push
Platform: any
Classifier: Programming Language :: Python :: 3
Classifier: License :: OSI Approved :: MIT License
Classifier: Intended Audience :: Developers
Classifier: Operating System :: OS Independent
Requires-Dist: requests
